tekmoney/__init__.py
tekmoney/currency.py
tekmoney/currency_range.py
tekmoney/currency_range_tax.py
tekmoney/currency_tax.py
tekmoney/discount.py
tekmoney/flat_tax.py
tekmoney/utils.py
tekmoney-1.1.dist-info/LICENSE
tekmoney-1.1.dist-info/METADATA
tekmoney-1.1.dist-info/WHEEL
tekmoney-1.1.dist-info/top_level.txt
tekmoney-1.1.dist-info/RECORD
