Metadata-Version: 2.1
Name: tekmoney
Version: 1.1
Summary: Handles money
Home-page: https://github.com/tek-shinobi/tekmoney
Author: tek shinobi
Author-email: hello@gmail.com
License: MIT
Keywords: money,currency
Platform: any
Classifier: Development Status :: 5 - Production/Stable
Classifier: Intended Audience :: Developers
Classifier: Topic :: Software Development :: Libraries :: Python Modules
Classifier: License :: OSI Approved :: MIT License
Classifier: Programming Language :: Python :: 3
Classifier: Programming Language :: Python :: 3.6
Classifier: Programming Language :: Python :: 3.7
Classifier: Programming Language :: Python :: 3.8
Classifier: Operating System :: OS Independent
Requires-Dist: babel (>=2.5.0)
Requires-Dist: typing (>=3.6.0)
